{"filename":"d0101.jpg", "regions":[{"marker":2,"isBubble":true, "features":{"pixCount":27388, "minX":175, "minY":11, "maxX":415, "maxY":176, "xRange":241, "yRange":166, "distBtwCenters":18.200274723201296, "blkPixPercent":0.0, "sumPix":0.0, "sdHoriz":0.0, "sdVert":0.0, "sdPix":0.0, "enclosed":true, "percentEnclosed":1.0, "percentArea":0.23688308612369363}},{"marker":3,"isBubble":false, "features":{"pixCount":1951, "minX":77, "minY":136, "maxX":157, "maxY":214, "xRange":81, "yRange":79, "distBtwCenters":13.509256086106296, "blkPixPercent":0.0, "sumPix":0.0, "sdHoriz":0.0, "sdVert":0.0, "sdPix":0.0, "enclosed":true, "percentEnclosed":1.0, "percentArea":0.03788968824940048}},{"marker":4,"isBubble":false, "features":{"pixCount":636, "minX":111, "minY":264, "maxX":154, "maxY":284, "xRange":44, "yRange":21, "distBtwCenters":2.692582403567252, "blkPixPercent":0.0, "sumPix":0.0, "sdHoriz":0.0, "sdVert":0.0, "sdPix":0.0, "enclosed":true, "percentEnclosed":1.0, "percentArea":0.005471178612665423}}]}
{"filename":"d0102.jpg", "regions":[{"marker":2,"isBubble":true, "features":{"pixCount":12375, "minX":86, "minY":9, "maxX":219, "maxY":153, "xRange":134, "yRange":145, "distBtwCenters":23.769728648009426, "blkPixPercent":0.0, "sumPix":0.0, "sdHoriz":0.0, "sdVert":0.0, "sdPix":0.0, "enclosed":true, "percentEnclosed":1.0, "percentArea":0.21481481481481482}},{"marker":3,"isBubble":false, "features":{"pixCount":3148, "minX":37, "minY":113, "maxX":137, "maxY":189, "xRange":101, "yRange":77, "distBtwCenters":12.658988901172163, "blkPixPercent":0.0, "sumPix":0.0, "sdHoriz":0.0, "sdVert":0.0, "sdPix":0.0, "enclosed":false, "percentEnclosed":0.6397163120567376, "percentArea":0.0859812050856827}}]}
{"filename":"d0103.jpg", "regions":[{"marker":2,"isBubble":true, "features":{"pixCount":24411, "minX":130, "minY":11, "maxX":373, "maxY":196, "xRange":244, "yRange":186, "distBtwCenters":18.607794065928395, "blkPixPercent":0.0, "sumPix":0.0, "sdHoriz":0.0, "sdVert":0.0, "sdPix":0.0, "enclosed":true, "percentEnclosed":1.0, "percentArea":0.24658516707416464}},{"marker":3,"isBubble":false, "features":{"pixCount":1006, "minX":210, "minY":322, "maxX":259, "maxY":354, "xRange":50, "yRange":33, "distBtwCenters":16.00781059358212, "blkPixPercent":0.0, "sumPix":0.0, "sdHoriz":0.0, "sdVert":0.0, "sdPix":0.0, "enclosed":false, "percentEnclosed":0.5042016806722689, "percentArea":0.008964955175224124}}]}
